abing/__init__.py
abing/main.py
abing/alembic/README
abing/alembic/env.py
abing/alembic/script.py.mako
abing/alembic/versions/09746a50372f_add_user_model.py
abing/alembic/versions/16bd2982f46e_first_migration.py
abing/alembic/versions/235757c5bc34_add_model_allocation.py
abing/alembic/versions/582710b9fab6_add_traffic_weight_column_to_arm_model.py
abing/alembic/versions/88b3cab99dfd_add_columns_created_and_updated_time.py
abing/alembic/versions/9f766facc4ab_change_experiment_schedule_data_type.py
abing/alembic/versions/ce5a475e1888_add_feature_model.py
abing/cli/__init__.py
abing/cli/alembic.ini
abing/core/__init__.py
abing/core/config.py
abing/core/exceptions.py
abing/core/security.py
abing/crud/__init__.py
abing/crud/base.py
abing/crud/crud_allocation.py
abing/crud/crud_arm.py
abing/crud/crud_experiment.py
abing/crud/crud_feature.py
abing/crud/crud_user.py
abing/db/__init__.py
abing/db/base.py
abing/db/base_class.py
abing/db/session.py
abing/models/__init__.py
abing/models/allocation.py
abing/models/arm.py
abing/models/experiment.py
abing/models/feature.py
abing/models/user.py
abing/routes/__init__.py
abing/routes/deps.py
abing/routes/v1/__init__.py
abing/routes/v1/api.py
abing/routes/v1/endpoints/__init__.py
abing/routes/v1/endpoints/allocation.py
abing/routes/v1/endpoints/arm.py
abing/routes/v1/endpoints/experiment.py
abing/routes/v1/endpoints/feature.py
abing/routes/v1/endpoints/login.py
abing/routes/v1/endpoints/user.py
abing/schemas/__init__.py
abing/schemas/allocation.py
abing/schemas/arm.py
abing/schemas/experiment.py
abing/schemas/feature.py
abing/schemas/message.py
abing/schemas/token.py
abing/schemas/user.py
abing/services/__init__.py
abing/services/route_service.py
abing/static/asset-manifest.json
abing/static/favicon.ico
abing/static/index.html
abing/static/logo192.png
abing/static/logo512.png
abing/static/manifest.json
abing/static/robots.txt
abing/static/static/.gitkeep
abing/static/static/css/2.4d98ed14.chunk.css
abing-0.1.2.dist-info/METADATA
abing-0.1.2.dist-info/WHEEL
abing-0.1.2.dist-info/entry_points.txt
abing-0.1.2.dist-info/top_level.txt
abing-0.1.2.dist-info/RECORD
