Metadata-Version: 2.1
Name: abing
Version: 0.1.2
Summary: Simply setup AB testing environment
Home-page: https://github.com/dohyungp/abing
Author: Dohyung Park
Author-email: dohyung.prk@gmail.com
License: UNKNOWN
Platform: any
Classifier: Programming Language :: Python :: 3
Classifier: License :: OSI Approved :: MIT License
Classifier: Operating System :: OS Independent
Requires-Python: >=3.6
Requires-Dist: fastapi
Requires-Dist: uvicorn
Requires-Dist: sqlalchemy
Requires-Dist: alembic
Requires-Dist: pydantic[email]
Requires-Dist: python-jose[cryptography]
Requires-Dist: passlib[bcrypt]
Requires-Dist: psycopg2-binary
Requires-Dist: xxhash
Requires-Dist: python-multipart
Requires-Dist: aiofiles
Requires-Dist: jinja2
Requires-Dist: click
Provides-Extra: sentry
Requires-Dist: sentry-sdk ; extra == 'sentry'
